
{
    "timeline":
    {
        "headline":"History through News",
        "type":"default",
		"startDate":"1914,1",
		"text":"<p>History through News is an application designed to give users an indepth view of a specific time period reconstructed through historical newspaper articles. The idea behind History through News is to extract from historical news articles information that will give the audience an understanding of what life is like during any time period in the past. In todays society, if we want to find out events that our society is interested in, social trends that are popular or foreign affairs that people are concerned about, we can easily find all these information via the internet and social networking websites. This is because many people owns a computer or a smart phone and they can easily voice their concerns by tweeting, posting on forums or update their Faceboook feed.</p><p>However, if we want to find similar information such as foreign events that concerns our society or what our society is interested prior to the invention of the computer and the internet, where do we find this information? During the pre-computer age, the most dominant form of communication and circulating information is via newspapers and our assumption is that we can find all these information from newspaper headlines. As an experiment, we downloaded about 250,000+ historical (Sydney Morning Herald) newspaper records via the Trove API. We applied Natural Language Processing (NLP) techniques on the newspaper headlines to extract vital information such as events, location, people etc. By performing statistical analysis on these extracted information, we calculated the most frequently used keywords found in headlines and use these keywords to find relevant articles and pictures to help identify what society cares most during that time period.</p><p>In our experiment, we found that during 1915-1919, there are alot of articles relating to the army, USA, germany, soldiers, food, invasion etc. From these keywords, it is very clear that during this time period there is a war happening and our society is most concerned with soldiers and food. We then fast tracked to another period in the 1924-1928 and in this period we see keywords such as tennis, olympic, football, golf etc. In comparison to the 1915-1919 period, this suggests that there are no war or disaster that happened and society focus more on recreational activities such the as the 1924 Olympic games. Finally, we performed the same experiment for the years between 1943-1945, we see the same similar patterns with 1915-1919. During this period of time, the keywords from headlines convey a very serious and depressing theme where most keywords are concerned with war, army, raid, battle etc.</p><p>From this experiment we found that by analysing newspaper articles we can extract vital information that can help the audience construct what life is like during any specific time period in the past. In addition, from the experiment we have created a catalog of newspaper article to keyword mappings which we are more than happy to open source it. These keywords can be added to the existing Trove dataset or can be used as tags for the articles. To properly display the contents on this webpage, please view on resolution 1920x1080.</p>",		
        "date": [
			{
                "startDate":"1915,10",
                "headline":"October - November 1915: Popular words in headlines",
                "text":"enemy, mining, balkans, south, campaign, death, soldiers, sporting, german, britain, paris, steamers, wool, gallipoli, bankruptcy, income, fire, chest, service, hospital",
                "asset":
                {
                    "media":"<div class='custom'><div class='graph' id='graph1'>placeholder</div><div class='images'><h3>Relevant Images</h3><div class='img-polaroid'><a href='http://trove.nla.gov.au/work/33027419'><img src='http://nla.gov.au/nla.pic-an23297148-t' alt='soldier'/><p>Armistice to bury [indicated with a white X] Turk with flag of truce - Turkish trenches just at his rear, [the Turk in question is just outside of the photograph, to the left of the soldier standing on the far left, June? 1915] J.P. Campbell</p></a></div><div class='img-polaroid'><a href='http://trove.nla.gov.au/work/36604352'><img src='http://143.119.202.10/_DAMl/image/23/135/a7436001r.jpg' alt='soldier'/><p>War meeting. A public meeting, School of Arts, Wyong, Wednesday, Sept. 1, 1915 8 p.m. To bid farewell to some of our departing soldier boys. Speakers: E.J. Loxton, K.C., J. Carlos, Barrister and Private H.H. Coates. All are invited</p></a></div><div class='img-polaroid'><a href='http://trove.nla.gov.au/work/153915846'><img src='http://bishop.slq.qld.gov.au:80/webclient/DeliveryManager?pid=202153' alt='soldier'/><p>Soldier J. Marsden, 1915</p></a></div><div class='img-polaroid'><a href='http://trove.nla.gov.au/work/36960326'><img src='http://museumvictoria.com.au/collections/ItemImages/153/266/153266_HoverThumb.jpg' alt='wool'/><p>Negative - Woolshed at 'Portland Downs' Station, Isisford District, Queensland, circa 1915</p></a></div></div><div class='articles'><div class='img-polaroid'><a href='http://trove.nla.gov.au/ndp/del/article/15627943'><h5>PRIZE COURT. (Before the Chief Justice (Sir Wm. Cullen.) ENEMY CARGO. Re The Tong King.</h5><p>The Sydney Morning Herald 1915-11-30</p></a></div><div class='img-polaroid'><a href='http://trove.nla.gov.au/ndp/del/article/15627913'><h5>THE BALKANS. FIERCE FIGHTING. THE BRITISH TROOPS. RELIEVE FRENCH IN DOIRAN REGION. LONDON, Nov. 29.</h5><p>The Sydney Morning Herald 1915-11-30</p></a></div><div class='img-polaroid'><a href='http://trove.nla.gov.au/ndp/del/article/15634393'><h5>AUSTRALIAN SOLDIERS IN LONDON. (BY OUR SPECIAL CORRESPONDENT.) THE ANZAC BUFFET. LONDON, Nov. 17.</h5><p>The Sydney Morning Herald 1915-12-31</p></a></div><div class='img-polaroid'><a href='http://trove.nla.gov.au/ndp/del/article/15634388'><h5>SPORTING. THE TURF.</h5><p>The Sydney Morning Herald 1915-11-30</p></a></div><div class='img-polaroid'><a href='http://trove.nla.gov.au/ndp/del/article/15627926'><h5>WHAT OF GALLIPOLI?</h5><p>The Sydney Morning Herald 1915-11-30</p></a></div></div></div>",
                    "credit":"",
                    "caption":""
                }
            },
			{
                "startDate":"1915,11",
                "headline":"November - December 1915: Popular words in headlines",
                "text":"enemy, death, telegraphic , recruiting, federal, balkans, mining, steamer, paris, german, greece, market, gallipoli, soldiers, water, sporting, soldier, railway, king, annexation",
                "asset":
                {
                    "media":"<div class='custom'><div class='graph' id='graph2'>placeholder</div><div class='images'><h3>Relevant Images</h3><div class='img-polaroid'><a href='http://trove.nla.gov.au/work/26388817'><img src='http://ark.cdlib.org/ark:/13030/kt909nc2mn/thumbnail' alt='telegraphic'/><p>Pacific Telephone & Telegraph Company, Orange Central Office, Orange, California, 1915</p></a></div><div class='img-polaroid'><a href='http://trove.nla.gov.au/work/161472632'><img src='http://recordsearch.naa.gov.au/scripts/SearchOld.asp?O=IMS2&S=1&Number=11369224' alt='gallipoli'/><p>The last party of the 2nd Australian Light Horse Brigade to leave the trenches at Gallipoli, December 1915</p></a></div><div class='img-polaroid'><a href='http://trove.nla.gov.au/work/37965278'><img src='http://library.coffsharbour.nsw.gov.au/picturecoffsharbour/mus07-2824t.jpg' alt='railway'/><p>Coffs Harbour to Raleigh Railway Opening Day, 30 August 1915</p></a></div><div class='img-polaroid'><a href='http://trove.nla.gov.au/work/29970078'><img src='http://content.lib.washington.edu/cgi-bin/thumbnail.exe?CISOROOT=/curtis&CISOPTR=400' alt='annexation'/><p>Shriner's parade on 2nd Ave., Seattle, July 13, 1915</p></a></div></div><div class='articles'><div class='img-polaroid'><a href='http://trove.nla.gov.au/ndp/del/article/15634520'><h5>THE BALKANS. MONTENEGRIN SUCCESS. HEAVY ENEMY LOSSES. LONDON, Dec. 30.</h5><p>The Sydney Morning Herald 1915-12-31</p></a></div><div class='img-polaroid'><a href='http://trove.nla.gov.au/ndp/del/article/15634496'><h5>NEW YEAR'S HOLIDAYS. POSTAL AND TELEGRAPHIC ARRANGEMENTS.</h5><p>The Sydney Morning Herald 1915-12-31</p></a></div><div class='img-polaroid'><a href='http://trove.nla.gov.au/ndp/del/article/15634399'><h5>FEDERAL SERVICE. MR. M'LACHLAN'S LAST REPORT.</h5><p>The Sydney Morning Herald 1915-12-31</p></a></div><div class='img-polaroid'><a href='http://trove.nla.gov.au/ndp/del/article/15634523'><h5>JAPANESE MAIL STEAMERS. TO USE CAPE ROUTE. TOKIO, Dec. 29.</h5><p>The Sydney Morning Herald 1915-12-31</p></a></div><div class='img-polaroid'><a href='http://trove.nla.gov.au/ndp/del/article/15634565'><h5>LATE WAR NEWS. DESTROYERS. SUNK BY THE ALLIES. PARIS, Dec. 30.</h5><p>The Sydney Morning Herald 1915-12-31</p></a></div></div></div>",
                    "credit":"",
                    "caption":""
                }
			},
			{
                "startDate":"1915,12",
                "headline":"December 1915 - January 1916: Popular words in headlines",
                "text":"christmas, death, trade , supreme, soldier, steamer, germany, lord, station, soldiers, school, railway, peace, king, hospital, butter, amsterdam, motor, speech, concert",
                "asset":
                {
                    "media":"<div class='custom'><div class='graph' id='graph3'>placeholder</div><div class='images'><h3>Relevant Images</h3><div class='img-polaroid'><a href='http://trove.nla.gov.au/work/152256428'><img src='http://bishop.slq.qld.gov.au:80/webclient/DeliveryManager?pid=502623' alt='christmas'/><p>Illustrated page from the Christmas supplement to The Queenslander, December 4, 1915, p. 76</p></a></div><div class='img-polaroid'><a href='http://trove.nla.gov.au/work/38059197'><img src='http://picture.ipswich.qld.gov.au/data/Library1/Picture Ipswich/Armed Forces/Wars/World War 1/THUMBNAIL/qips-2009-04-27-0013p.jpg' alt='soldier'/><p>Postcard from Ipswich, soldier, William Johnson, enroute to Europe, 1915</p></a></div><div class='img-polaroid'><a href='http://trove.nla.gov.au/work/167541541'><img src='http://digital.slv.vic.gov.au/webclient/DeliveryManager?pid=1340698' alt='amsterdam'/><p>[View of barges on river, Amsterdam]</p></a></div><div class='img-polaroid'><a href='http://trove.nla.gov.au/work/37436185'><img src='http://library.coffsharbour.nsw.gov.au/picturecoffsharbour/mus07-2752t.jpg' alt='motor'/><p>Motor Vehicle 1915?</p></a></div></div><div class='articles'><div class='img-polaroid'><a href='http://trove.nla.gov.au/ndp/del/article/15633823'><h5>CHRISTMAS. CELEBRATIONS IN THE STATE. THE GREAT YEAR OF WAR.</h5><p>The Sydney Morning Herald 1915-12-27</p></a></div><div class='img-polaroid'><a href='http://trove.nla.gov.au/ndp/del/article/15634428'><h5>TRADES AND LABOUR. WATERSIDE CLERKS' CLAIMS.</h5><p>The Sydney Morning Herald 1915-12-31</p></a></div><div class='img-polaroid'><a href='http://trove.nla.gov.au/ndp/del/article/15634464'><h5>LAW NOTICES. TUESDAY, JANUARY 4. SUPREME COURT.</h5><p>The Sydney Morning Herald 1915-12-31</p></a></div><div class='img-polaroid'><a href='http://trove.nla.gov.au/ndp/del/article/15634206'><h5>THE ALLIES' DUTY TO GERMANY. TO THE EDITOR OF THE HERALD.</h5><p>The Sydney Morning Herald 1915-12-30</p></a></div><div class='img-polaroid'><a href='http://trove.nla.gov.au/ndp/del/article/15634370'><h5>RAILWAY AND TRAMWAY MEN. UNIONS CONFER.</h5><p>The Sydney Morning Herald 1915-12-31</p></a></div></div></div>",
                    "credit":"",
                    "caption":""
                }
			},
			{
                "startDate":"1924,06",
                "headline":"June - July 1924: Popular words in headlines",
                "text":"tennis, interstate, labour , match, school, tournament, golf, cricket, company, death, railway, team, championship, university, wheat, olympic, perth, cable, football, wireless",
                "asset":
                {
                    "media":"<div class='custom'><div class='graph' id='graph13'>placeholder</div><div class='images'><h3>Relevant Images</h3><div class='img-polaroid'><a href='http://trove.nla.gov.au/work/153931535'><img src='http://bishop.slq.qld.gov.au:80/webclient/DeliveryManager?pid=291537&custom_att_2=simple_viewer' alt='tennis'/><p>Kin Kin premiership tennis team, 1924</p></a></div><div class='img-polaroid'><a href='http://trove.nla.gov.au/work/168587283'><img src='http://www.photosau.com.au/WilloughbyLib/Jthumb/001/001745.jpg' alt='cricket'/><p>Willoughby District Cricket Club, 1924-1925</p></a></div><div class='img-polaroid'><a href='http://trove.nla.gov.au/work/37760450'><img src='http://www.photosau.com.au/Manlylib/Jthumb/004/004009.jpg' alt='olympic'/><p>Welcome home to Manly's Olympic representatives, 1924</p></a></div><div class='img-polaroid'><a href='http://trove.nla.gov.au/work/37436185'><img src='http://www.photosau.com.au/WilloughbyLib/Jthumb/0011/0011222.jpg' alt='wireless'/><p>Wireless Estate No. 3 on the glorious foreshores of Middle Harbour (Willoughby), 29th November (1924?)</p></a></div></div><div class='articles'><div class='img-polaroid'><a href='http://trove.nla.gov.au/ndp/del/article/16171856'><h5>LAWN TENNIS. METROPOLIS V. STANFORD UNIVERSITY. VISITORS BEATEN.</h5><p>The Sydney Morning Herald 1924-07-28</p></a></div><div class='img-polaroid'><a href='http://trove.nla.gov.au/ndp/del/article/16171851'><h5>WESTCOURT NIGHT TOURNAMENT.</h5><p>The Sydney Morning Herald 1924-07-28</p></a></div><div class='img-polaroid'><a href='http://trove.nla.gov.au/ndp/del/article/16175693'><h5>GOLF. MILLIONS CLUB CHAMPIONSHIP.</h5><p>The Sydney Morning Herald 1924-07-29</p></a></div><div class='img-polaroid'><a href='http://trove.nla.gov.au/ndp/del/article/16171985'><h5>CRICKET. ENGLAND'S BEST COVERPOINT</h5><p>The Sydney Morning Herald 1924-07-28</p></a></div><div class='img-polaroid'><a href='http://trove.nla.gov.au/ndp/del/article/16172004'><h5>OLYMPIC CYCLING. 1000 METRES HEATS. Dempsey and Coppins Win. LONDON, July 27.</h5><p>The Sydney Morning Herald 1924-07-28</p></a></div></div></div>",
                    "credit":"",
                    "caption":""
                }
			},
			{
                "startDate":"1928,02",
                "headline":"February - March 1928: Popular words in headlines",
                "text":"motor, market, country , death, exchange, n.z., wellington, racing, exhibition, wheat, american, tour, trade, wool, cricket, britain, football, railway, theatre, university",
                "asset":
                {
                    "media":"<div class='custom'><div class='graph' id='graph14'>placeholder</div><div class='images'><h3>Relevant Images</h3><div class='img-polaroid'><a href='http://trove.nla.gov.au/work/153993052'><img src='http://bishop.slq.qld.gov.au:80/webclient/DeliveryManager?pid=446205' alt='motor'/><p>New England Motor Co. bus on the Brisbane to Grafton run, ca 1928</p></a></div><div class='img-polaroid'><a href='http://trove.nla.gov.au/work/15625503'><img src='http://www.slwa.wa.gov.au/images/pd226/226,374PD.png' alt='racing'/><p>Motor racing on Lake Perkolilli, November 1928</p></a></div><div class='img-polaroid'><a href='http://trove.nla.gov.au/work/38861804'><img src='http://nla.gov.au/nla.pic-vn5125945-t' alt='wheat'/><p>Loading wheat from rail trucks to ships, Melbourne, ca. 1928</p></a></div><div class='img-polaroid'><a href='http://trove.nla.gov.au/work/36928978'><img src='http://bishop.slq.qld.gov.au:80/webclient/DeliveryManager?pid=44873' alt='railway'/><p>Arrival of the train to Atherton Railway Station, Queensland, 1928</p></a></div></div><div class='articles'><div class='img-polaroid'><a href='http://trove.nla.gov.au/ndp/del/article/16453615'><h5>MOTOR CHASSIS. TARIFF SCHEDULE AMENDMENT.</h5><p>The Sydney Morning Herald 1928-03-31</p></a></div><div class='img-polaroid'><a href='http://trove.nla.gov.au/ndp/del/article/16453560'><h5>MINING. THE SHARE MARKET.</h5><p>The Sydney Morning Herald 1928-03-31</p></a></div><div class='img-polaroid'><a href='http://trove.nla.gov.au/ndp/del/article/16453559'><h5>LONDON STOCK EXCHANGE. LONDON, March 29.</h5><p>The Sydney Morning Herald 1928-03-31</p></a></div><div class='img-polaroid'><a href='http://trove.nla.gov.au/ndp/del/article/16453288'><h5>GREYHOUND RACING. RECORD AT MASCOT.</h5><p>The Sydney Morning Herald 1928-03-30</p></a></div><div class='img-polaroid'><a href='http://trove.nla.gov.au/ndp/del/article/16453783'><h5>UNIVERSITY PAGEANT.</h5><p>The Sydney Morning Herald 1928-03-31</p></a></div></div></div>",
                    "credit":"",
                    "caption":""
                }
			},
			{
                "startDate":"1935,11",
                "headline":"November - December 1935: Popular words in headlines",
                "text":"christmas, death, mail, gold, wheat, newcastle, strike, team, zealand, fire, racing, port, park, wool, school, party, speech, hospital, murder, england",
                "asset":
                {
                    "media":"<div class='custom'><div class='graph' id='graph15'>placeholder</div><div class='images'><h3>Relevant Images</h3><div class='img-polaroid'><a href='http://trove.nla.gov.au/work/173726797'><img src='http://www.nma.gov.au/collections-search/media?image=yes&size=med&irn=57900' alt='christmas'/><p>Christmas card from Betty Archdale to Ruby Monaghan, 1935</p></a></div><div class='img-polaroid'><a href='http://trove.nla.gov.au/work/36893348'><img src='http://bishop.slq.qld.gov.au:80/webclient/DeliveryManager?pid=47874' alt='mail'/><p>Royal Air Mail plane delivering the first mail to Rockhampton, ca. 1935</p></a></div><div class='img-polaroid'><a href='http://trove.nla.gov.au/work/153915387'><img src='http://bishop.slq.qld.gov.au:80/webclient/DeliveryManager?pid=63573' alt='strike'/><p>Group of picketers riding in a car during a strike in 1935</p></a></div><div class='img-polaroid'><a href='http://trove.nla.gov.au/work/28187283'><img src='http://nla.gov.au/nla.pic-vn4654329-t' alt='murder'/><p>Portrait of Patrick Brady convicted murderer in the Shark Arm case, ca 1935 / E.W. Searle</p></a></div></div><div class='articles'><div class='img-polaroid'><a href='http://trove.nla.gov.au/ndp/del/article/17224125'><h5>GENERAL CABLE NEWS. CHRISTMAS POSTAL FIGURES. LONDON, Dec. 29.</h5><p>The Sydney Morning Herald 1935-12-30</p></a></div><div class='img-polaroid'><a href='http://trove.nla.gov.au/ndp/del/article/17208728'><h5>BURNT TO DEATH. THREE WOMEN IN HOTEL FIRE. LONDON, Dec. 30.</h5><p>The Sydney Morning Herald 1935-12-31</p></a></div><div class='img-polaroid'><a href='http://trove.nla.gov.au/ndp/del/article/17208887'><h5>GOLD QUOTATION.</h5><p>The Sydney Morning Herald 1935-12-31</p></a></div><div class='img-polaroid'><a href='http://trove.nla.gov.au/ndp/del/article/17208840'><h5>SICK LIGHTHOUSE KEEPER. Delay in Transportation to Hospital. LAUNCESTON, Monday.</h5><p>The Sydney Morning Herald 1935-12-31</p></a></div><div class='img-polaroid'><a href='http://trove.nla.gov.au/ndp/del/article/17208940'><h5>MURDER AND SUICIDE. Letters Read at Inquest. ITALIAN'S MYSTERIOUS REASON.</h5><p>The Sydney Morning Herald 1935-12-31</p></a></div></div></div>",
                    "credit":"",
                    "caption":""
                }
			},
			{
                "startDate":"1942,12",
                "headline":"December 1942 - January 1943: Popular words in headlines",
                "text":"u.s., army, enemy, inquiry, raid, tunisia, attack, r.a.a.f., africa, a.i.f., caucasus, man-power, nazi, strike, japan, roosevelt, pacific, milk, charles, buttrose",
                "asset":
                {
                    "media":"<div class='custom'><div class='graph' id='graph4'>placeholder</div><div class='images'><h3>Relevant Images</h3><div class='img-polaroid'><a href='http://trove.nla.gov.au/work/154907958'><img src='http://museumvictoria.com.au/collections/ItemImages/243/422/243422_HoverThumb.jpg' alt='army'/><p>Digital Photograph - 'Goodbye to Jean Buckley, Off to the Land Army', Coburg, 1943</p></a></div><div class='img-polaroid'><a href='http://trove.nla.gov.au/work/33479750'><img src='http://nla.gov.au/nla.pic-an23529718-t' alt='r.a.a.f.'/><p>[The Southern Cross aeroplane on the airfield amongst other planes, RAAF Base Fairbairn, Canberra, A.C.T., 1943?]</p></a></div><div class='img-polaroid'><a href='http://trove.nla.gov.au/work/80920183'><img src='http://bishop.slq.qld.gov.au:80/webclient/DeliveryManager?pid=446237' alt='roosevelt'/><p>Eleanor Roosevelt greeted on arrival to Rockhampton by officials, 1943</p></a></div><div class='img-polaroid'><a href='http://trove.nla.gov.au/work/152853655'><img src='http://static.flickr.com/3119/2783875664_08d3dea568_t.jpg' alt='a.i.f.'/><p>2/13th Battalion AIF July 1943</p></a></div></div><div class='articles'><div class='img-polaroid'><a href='http://trove.nla.gov.au/ndp/del/article/17833820'><h5>MEDICAL SOCIETY'S CONVICTION U.S. SUPREME COURT</h5><p>The Sydney Morning Herald 1943-01-20</p></a></div><div class='img-polaroid'><a href='http://trove.nla.gov.au/ndp/del/article/17833650'><h5>JAPANESE NEAR END AT SANANANDA 'A Disillusioned, Shattered Army'</h5><p>The Sydney Morning Herald 1943-01-19</p></a></div><div class='img-polaroid'><a href='http://trove.nla.gov.au/ndp/del/article/17833829'><h5>LUFTWAFFE'S FAILURE IN LONDON RAIDS THE 'BATTLE OF THE CAPITALS' From Our Staff Correspondent</h5><p>The Sydney Morning Herald 1943-01-20</p></a></div><div class='img-polaroid'><a href='http://trove.nla.gov.au/ndp/del/article/17833973'><h5>GIRL SHOT DEAD IN SHELTER R.A.A.F. Man for Trial</h5><p>The Sydney Morning Herald 1943-01-21</p></a></div><div class='img-polaroid'><a href='http://trove.nla.gov.au/ndp/del/article/17833569'><h5>ENEMY POST CRACKED SUDDENLY From Our War Correspondent, Charles Buttrose</h5><p>The Sydney Morning Herald 1943-01-18</p></a></div></div></div>",
                    "credit":"",
                    "caption":""
                }
			},
			{
                "startDate":"1943,2",
                "headline":"Feburary - March 1943: Popular words in headlines",
                "text":"army, u.s., loan, pacific, mareth, attack, battle, raid, burma, enemy, food, soviet, bread, gold, rugby, league, union, milk, churchill, hughes",
                "asset":
                {
                    "media":"<div class='custom'><div class='graph' id='graph5'>placeholder</div><div class='images'><h3>Relevant Images</h3><div class='img-polaroid'><a href='http://trove.nla.gov.au/work/37511683'><img src='http://www.slwa.wa.gov.au/images/pd221/221,484PD.png' alt='loan'/><p>Youth organisations taking part in War Loan Rally demonstrations in Perth, 27 October 1943 [picture]</p></a></div><div class='img-polaroid'><a href='http://trove.nla.gov.au/work/36910610'><img src='http://bishop.slq.qld.gov.au:80/webclient/DeliveryManager?pid=93086' alt='burma'/><p>William Gerrard of RAF 117 Squadron is organising the supply drop for the Chindits, Burma, ca. 1943</p></a></div><div class='img-polaroid'><a href='http://trove.nla.gov.au/work/27289983'><img src='http://photos.salemhistory.net/cgi-bin/thumbnail.exe?CISOROOT=/max&CISOPTR=4498' alt='food'/><p>Food products that could be purchased during World War II with food rationing stamps, 1943</p></a></div><div class='img-polaroid'><a href='http://trove.nla.gov.au/work/33524343'><img src='http://nla.gov.au/nla.pic-vn4319630-t' alt='churchill'/><p>General Sir Alan Brooke, Air Chief Marshal Sir Sholto Douglas, R.G. Casey, Sir Winston Churchill, Sir Miles Lampson and Major Randolph Churchill (from left to right) at the Minister of State's house, Cairo, January 1943</p></a></div></div><div class='articles'><div class='img-polaroid'><a href='http://trove.nla.gov.au/ndp/del/article/17842496'><h5>EIGHTH ARMY TAKES GABES</h5><p>The Sydney Morning Herald 1943-03-31</p></a></div><div class='img-polaroid'><a href='http://trove.nla.gov.au/ndp/del/article/17842542'><h5>U.S. SERVICEMEN'S WIVES Position Explained by Mrs. Roosevelt</h5><p>The Sydney Morning Herald 1943-03-31</p></a></div><div class='img-polaroid'><a href='http://trove.nla.gov.au/ndp/del/article/17842382'><h5>FOOD PRODUCTION CENSUS</h5><p>The Sydney Morning Herald 1943-03-30</p></a></div><div class='img-polaroid'><a href='http://trove.nla.gov.au/ndp/del/article/17842577'><h5>NEW ZEALANDERS PASS THROUGH GABES OTHER GAINS IN TUNISIA CHURCHILL TELLS OF AIR BLITZ From Our Staff Correspondents and A.A.P.</h5><p>The Sydney Morning Herald 1943-03-31</p></a></div><div class='img-polaroid'><a href='http://trove.nla.gov.au/ndp/del/article/17842389'><h5>'SHEER NONSENSE,' MR. HUGHES SAYS</h5><p>The Sydney Morning Herald 1943-03-30</p></a></div></div></div>",
                    "credit":"",
                    "caption":""
                }
			},
			{
                "startDate":"1943,3",
                "headline":"March - April 1943: Popular words in headlines",
                "text":"u.s., army, raid, loan, tunisia, pacific, britain, union, oversea, enemy, strike, appeal, price, food, rugby, r.a.f., japan, sport, threat, rommel",
                "asset":
                {
                    "media":"<div class='custom'><div class='graph' id='graph6'>placeholder</div><div class='images'><h3>Relevant Images</h3><div class='img-polaroid'><a href='http://trove.nla.gov.au/work/167145437'><img src='http://digital.slv.vic.gov.au/webclient/DeliveryManager?pid=2061920' alt='tunisia'/><p>Mussolini as R.A.F. mess mascot in Tunisia</p></a></div><div class='img-polaroid'><a href='http://trove.nla.gov.au/work/167566799'><img src='http://digital.slv.vic.gov.au/webclient/DeliveryManager?pid=2788265' alt='britain'/><p>H.M.A.S. 'SHROPSHIRE' - BRITAIN'S GIFT TO AUSTRALIA - REFITS AT BRITISH PORT</p></a></div><div class='img-polaroid'><a href='http://trove.nla.gov.au/work/37038107'><img src='http://collections.ncc.nsw.gov.au/keemu/objects/common/webmedia.php?irn=26505&thumb=yes' alt='ruby'/><p>Second Thirteen, 1943 Newcastle Boys High School, runners up for the Dodd Shield</p></a></div><div class='img-polaroid'><a href='http://trove.nla.gov.au/work/13030678'><img src='http://www.slwa.wa.gov.au/images/pd047/047,106PD.png' alt='japan'/><p>The first prisoner of war letter from Japan to Western Australia was from Private J. S. Livingstone to his mother</p></a></div></div><div class='articles'><div class='img-polaroid'><a href='http://trove.nla.gov.au/ndp/del/article/17845239'><h5>Women's News TWENTY U.S. WAR WORKERS New Arrivals</h5><p>The Sydney Morning Herald 1943-04-21</p></a></div><div class='img-polaroid'><a href='http://trove.nla.gov.au/ndp/del/article/17844384'><h5>WAR LOAN</h5><p>The Sydney Morning Herald 1943-04-15</p></a></div><div class='img-polaroid'><a href='http://trove.nla.gov.au/ndp/del/article/17845280'><h5>THE WAR, DAY BY DAY Aerial Blockade of Tunisia By Our Military Correspondent,</h5><p>The Sydney Morning Herald 1943-04-21</p></a></div><div class='img-polaroid'><a href='http://trove.nla.gov.au/ndp/del/article/17845061'><h5>C.C.C. MEN FINED Sequel to Strike</h5><p>The Sydney Morning Herald 1943-04-20</p></a></div><div class='img-polaroid'><a href='http://trove.nla.gov.au/ndp/del/article/17844532'><h5>ROMMEL AS A 'GUEST' 'Simple Life' at Sfax Villa OUR WAR CORRESPONDENT, WILUAM MUNDAY.</h5><p>The Sydney Morning Herald 1943-04-15</p></a></div></div></div>",
                    "credit":"",
                    "caption":""
                }
			},
			{
                "startDate":"1943,5",
                "headline":"May - June 1943: Popular words in headlines",
                "text":"u.s., army, curtin, food, home, labour, rugby, strike, union, pantellaria, invasion, ration, policy, butter, w.e.a., bomber, boxing, king, naval, coal",
                "asset":
                {
                    "media":"<div class='custom'><div class='graph' id='graph7'>placeholder</div><div class='images'><h3>Relevant Images</h3><div class='img-polaroid'><a href='http://trove.nla.gov.au/work/20730789'><img src='http://nla.gov.au/nla.pic-vn3601808-t' alt='curtin'/><p>Portrait of John Curtin with Eleanor Roosevelt at a state luncheon, Parliament House, Canberra, September 1943</p></a></div><div class='img-polaroid'><a href='http://trove.nla.gov.au/work/28757040'><img src='http://quod.lib.umich.edu/u/ummu/thumb/8/5/4/08_02854.jpg' alt='strike'/><p>Oil Strike</p></a></div><div class='img-polaroid'><a href='http://trove.nla.gov.au/work/30148915'><img src='http://content.lib.washington.edu/cgi-bin/thumbnail.exe?CISOROOT=/imlsmohai&CISOPTR=185' alt='butter'/><p>Customers waiting to buy butter at Shepherd's Grocery, Seattle, 1943</p></a></div><div class='img-polaroid'><a href='http://trove.nla.gov.au/work/20533811'><img src='http://nla.gov.au/nla.pic-vn3723172-t' alt='bomber'/><p>Portrait of Flight Lieutenant Peter Isaacson, DFC, AFC, DFM, captain of the first Lancaster bomber to visit Australia, 1943</p></a></div></div><div class='articles'><div class='img-polaroid'><a href='http://trove.nla.gov.au/ndp/del/article/17852599'><h5>PRODUCTION EXPANDS U.S. Industrial Achievement</h5><p>The Sydney Morning Herald 1943-06-14</p></a></div><div class='img-polaroid'><a href='http://trove.nla.gov.au/ndp/del/article/17852549'><h5>MR. CURTIN FIRM ON WAR VIEW</h5><p>The Sydney Morning Herald 1943-06-14</p></a></div><div class='img-polaroid'><a href='http://trove.nla.gov.au/ndp/del/article/17852189'><h5>DRIVE FOR FOOD PRODUCTION Targets for States</h5><p>The Sydney Morning Herald 1943-06-11</p></a></div><div class='img-polaroid'><a href='http://trove.nla.gov.au/ndp/del/article/17852589'><h5>THE WAR, DAY BY DAY Tactical Lessons of Pantellaria By Our Military Correspondent.</h5><p>The Sydney Morning Herald 1943-06-14</p></a></div><div class='img-polaroid'><a href='http://trove.nla.gov.au/ndp/del/article/17852588'><h5>VEGETABLE CUT FEARED Half Rations If No Improvement BY OUR AGRICULTURAL EDITOR.</h5><p>The Sydney Morning Herald 1943-06-14</p></a></div></div></div>",
                    "credit":"",
                    "caption":""
                }
			}, 			
			{
                "startDate":"1943,11",
                "headline":"November - December 1943: Popular words in headlines",
                "text":"u.s., army, christmas, enemy, britain, attack, italy, meat, holiday, nazi, raid, russia, japan, peace, churchill, kiev, gloucester, king, a.l.p., hospital",
                "asset":
                {
                    "media":"<div class='custom'><div class='graph' id='graph12'>placeholder</div><div class='images'><h3>Relevant Images</h3><div class='img-polaroid'><a href='http://trove.nla.gov.au/work/27324325'><img src='http://photos.salemhistory.net/cgi-bin/thumbnail.exe?CISOROOT=/mchs&CISOPTR=323' alt='christmas'/><p>Christmas 1943 dinner at the Oregon State Fairgrounds in Salem, Oregon</p></a></div><div class='img-polaroid'><a href='http://trove.nla.gov.au/work/30162746'><img src='http://content.lib.washington.edu/cgi-bin/thumbnail.exe?CISOROOT=/imlsmohai&CISOPTR=3621' alt='meat'/><p>Butchers working at meat market, Seattle, February 20, 1943</p></a></div><div class='img-polaroid'><a href='http://trove.nla.gov.au/work/37498606'><img src='http://nla.gov.au/nla.pic-vn4925500-t' alt='king'/><p>Palace of King Faisal II of Iraq, Baghdad, Iraq, ca. 1943 / Frank Hurley</p></a></div><div class='img-polaroid'><a href='http://trove.nla.gov.au/work/37890125'><img src='http://nla.gov.au/nla.pic-vn4962951-t' alt='hospital'/><p>Australian hospital ship, Centaur, 1943</p></a></div></div><div class='articles'><div class='img-polaroid'><a href='http://trove.nla.gov.au/ndp/del/article/17879689'><h5>U.S. FLAG FOR SYDNEY San Francisco's Gift</h5><p>The Sydney Morning Herald 1943-12-31</p></a></div><div class='img-polaroid'><a href='http://trove.nla.gov.au/ndp/del/article/17870076'><h5>CHRISTMAS IN THE JUNGLE Active Service Conditions</h5><p>The Sydney Morning Herald 1943-12-30</p></a></div><div class='img-polaroid'><a href='http://trove.nla.gov.au/ndp/del/article/17879757'><h5>SUPERIOR NAZI NAVAL FORCE ROUTED Two Cruisers Against 11 Destroyers</h5><p>The Sydney Morning Herald 1943-12-31</p></a></div><div class='img-polaroid'><a href='http://trove.nla.gov.au/ndp/del/article/17879723'><h5>'REST FOR FEW WEEKS' Message From Mr. Churchill</h5><p>The Sydney Morning Herald 1943-12-31</p></a></div><div class='img-polaroid'><a href='http://trove.nla.gov.au/ndp/del/article/17872107'><h5>A.L.P.'S EMPIRE SPIRIT Conference In Retrospect MR. CURTIN'S RESOLUTION</h5><p>The Sydney Morning Herald 1943-12-20</p></a></div></div></div>",
                    "credit":"",
                    "caption":""
                }
			}
        ]
    }
}